kyops/__init__.py
kyops/n_dict.py
kyops-0.1.1.dist-info/WHEEL
kyops-0.1.1.dist-info/METADATA
kyops-0.1.1.dist-info/RECORD
