Metadata-Version: 2.1
Name: kyops
Version: 0.1.1
Summary: kyops Python library for performing operations on data structures in python
License: MIT
Author-email: KOUASSI Yves <kouassives@gmail.com>
Requires-Python: >=3.8
Project-URL: homepage, https://github.com/kouassives/kyops/tree/main/Python
